<annotation>
	<folder>FINAL_XML_DATASET_NEW</folder>
	<filename>144_001.png</filename>
	<path>/media/ivliev/DISK/_dataset/FINAL_XML_DATASET_NEW/144_001.png</path>
	<source>
		<database>Unknown</database>
	</source>
	<size>
		<width>800</width>
		<height>800</height>
		<depth>3</depth>
	</size>
	<segmented>0</segmented>
	<object>
		<name>weed</name>
		<pose>Unspecified</pose>
		<truncated>1</truncated>
		<difficult>0</difficult>
		<bndbox>
			<xmin>1</xmin>
			<ymin>207</ymin>
			<xmax>122</xmax>
			<ymax>313</ymax>
		</bndbox>
	</object>
	<object>
		<name>weed</name>
		<pose>Unspecified</pose>
		<truncated>0</truncated>
		<difficult>0</difficult>
		<bndbox>
			<xmin>281</xmin>
			<ymin>210</ymin>
			<xmax>410</xmax>
			<ymax>322</ymax>
		</bndbox>
	</object>
	<object>
		<name>weed</name>
		<pose>Unspecified</pose>
		<truncated>0</truncated>
		<difficult>0</difficult>
		<bndbox>
			<xmin>557</xmin>
			<ymin>226</ymin>
			<xmax>680</xmax>
			<ymax>353</ymax>
		</bndbox>
	</object>
	<object>
		<name>spikelet</name>
		<pose>Unspecified</pose>
		<truncated>0</truncated>
		<difficult>0</difficult>
		<bndbox>
			<xmin>187</xmin>
			<ymin>468</ymin>
			<xmax>260</xmax>
			<ymax>519</ymax>
		</bndbox>
	</object>
	<object>
		<name>spikelet</name>
		<pose>Unspecified</pose>
		<truncated>1</truncated>
		<difficult>0</difficult>
		<bndbox>
			<xmin>606</xmin>
			<ymin>1</ymin>
			<xmax>641</xmax>
			<ymax>34</ymax>
		</bndbox>
	</object>
	<object>
		<name>spikelet</name>
		<pose>Unspecified</pose>
		<truncated>0</truncated>
		<difficult>0</difficult>
		<bndbox>
			<xmin>340</xmin>
			<ymin>422</ymin>
			<xmax>383</xmax>
			<ymax>491</ymax>
		</bndbox>
	</object>
	<object>
		<name>spikelet</name>
		<pose>Unspecified</pose>
		<truncated>0</truncated>
		<difficult>0</difficult>
		<bndbox>
			<xmin>380</xmin>
			<ymin>672</ymin>
			<xmax>423</xmax>
			<ymax>717</ymax>
		</bndbox>
	</object>
	<object>
		<name>spikelet</name>
		<pose>Unspecified</pose>
		<truncated>0</truncated>
		<difficult>0</difficult>
		<bndbox>
			<xmin>318</xmin>
			<ymin>610</ymin>
			<xmax>356</xmax>
			<ymax>657</ymax>
		</bndbox>
	</object>
	<object>
		<name>spikelet</name>
		<pose>Unspecified</pose>
		<truncated>0</truncated>
		<difficult>0</difficult>
		<bndbox>
			<xmin>351</xmin>
			<ymin>620</ymin>
			<xmax>385</xmax>
			<ymax>675</ymax>
		</bndbox>
	</object>
	<object>
		<name>spikelet</name>
		<pose>Unspecified</pose>
		<truncated>0</truncated>
		<difficult>0</difficult>
		<bndbox>
			<xmin>631</xmin>
			<ymin>593</ymin>
			<xmax>668</xmax>
			<ymax>640</ymax>
		</bndbox>
	</object>
	<object>
		<name>spikelet</name>
		<pose>Unspecified</pose>
		<truncated>0</truncated>
		<difficult>0</difficult>
		<bndbox>
			<xmin>133</xmin>
			<ymin>623</ymin>
			<xmax>181</xmax>
			<ymax>675</ymax>
		</bndbox>
	</object>
	<object>
		<name>spikelet</name>
		<pose>Unspecified</pose>
		<truncated>1</truncated>
		<difficult>0</difficult>
		<bndbox>
			<xmin>156</xmin>
			<ymin>1</ymin>
			<xmax>195</xmax>
			<ymax>43</ymax>
		</bndbox>
	</object>
	<object>
		<name>spikelet</name>
		<pose>Unspecified</pose>
		<truncated>0</truncated>
		<difficult>0</difficult>
		<bndbox>
			<xmin>178</xmin>
			<ymin>634</ymin>
			<xmax>214</xmax>
			<ymax>674</ymax>
		</bndbox>
	</object>
	<object>
		<name>spikelet</name>
		<pose>Unspecified</pose>
		<truncated>0</truncated>
		<difficult>0</difficult>
		<bndbox>
			<xmin>714</xmin>
			<ymin>39</ymin>
			<xmax>755</xmax>
			<ymax>85</ymax>
		</bndbox>
	</object>
	<object>
		<name>spikelet</name>
		<pose>Unspecified</pose>
		<truncated>0</truncated>
		<difficult>0</difficult>
		<bndbox>
			<xmin>562</xmin>
			<ymin>28</ymin>
			<xmax>599</xmax>
			<ymax>72</ymax>
		</bndbox>
	</object>
	<object>
		<name>spikelet</name>
		<pose>Unspecified</pose>
		<truncated>1</truncated>
		<difficult>0</difficult>
		<bndbox>
			<xmin>1</xmin>
			<ymin>5</ymin>
			<xmax>30</xmax>
			<ymax>51</ymax>
		</bndbox>
	</object>
	<object>
		<name>spikelet</name>
		<pose>Unspecified</pose>
		<truncated>0</truncated>
		<difficult>0</difficult>
		<bndbox>
			<xmin>101</xmin>
			<ymin>497</ymin>
			<xmax>150</xmax>
			<ymax>539</ymax>
		</bndbox>
	</object>
	<object>
		<name>spikelet</name>
		<pose>Unspecified</pose>
		<truncated>0</truncated>
		<difficult>0</difficult>
		<bndbox>
			<xmin>3</xmin>
			<ymin>575</ymin>
			<xmax>48</xmax>
			<ymax>611</ymax>
		</bndbox>
	</object>
	<object>
		<name>spikelet</name>
		<pose>Unspecified</pose>
		<truncated>0</truncated>
		<difficult>0</difficult>
		<bndbox>
			<xmin>347</xmin>
			<ymin>510</ymin>
			<xmax>395</xmax>
			<ymax>554</ymax>
		</bndbox>
	</object>
	<object>
		<name>spikelet</name>
		<pose>Unspecified</pose>
		<truncated>0</truncated>
		<difficult>0</difficult>
		<bndbox>
			<xmin>740</xmin>
			<ymin>536</ymin>
			<xmax>786</xmax>
			<ymax>574</ymax>
		</bndbox>
	</object>
	<object>
		<name>spikelet</name>
		<pose>Unspecified</pose>
		<truncated>0</truncated>
		<difficult>0</difficult>
		<bndbox>
			<xmin>563</xmin>
			<ymin>103</ymin>
			<xmax>605</xmax>
			<ymax>135</ymax>
		</bndbox>
	</object>
	<object>
		<name>spikelet</name>
		<pose>Unspecified</pose>
		<truncated>1</truncated>
		<difficult>0</difficult>
		<bndbox>
			<xmin>767</xmin>
			<ymin>205</ymin>
			<xmax>800</xmax>
			<ymax>239</ymax>
		</bndbox>
	</object>
	<object>
		<name>spikelet</name>
		<pose>Unspecified</pose>
		<truncated>0</truncated>
		<difficult>0</difficult>
		<bndbox>
			<xmin>659</xmin>
			<ymin>52</ymin>
			<xmax>693</xmax>
			<ymax>87</ymax>
		</bndbox>
	</object>
	<object>
		<name>spikelet</name>
		<pose>Unspecified</pose>
		<truncated>0</truncated>
		<difficult>0</difficult>
		<bndbox>
			<xmin>693</xmin>
			<ymin>581</ymin>
			<xmax>732</xmax>
			<ymax>633</ymax>
		</bndbox>
	</object>
	<object>
		<name>spikelet</name>
		<pose>Unspecified</pose>
		<truncated>0</truncated>
		<difficult>0</difficult>
		<bndbox>
			<xmin>273</xmin>
			<ymin>565</ymin>
			<xmax>307</xmax>
			<ymax>599</ymax>
		</bndbox>
	</object>
	<object>
		<name>spikelet</name>
		<pose>Unspecified</pose>
		<truncated>0</truncated>
		<difficult>0</difficult>
		<bndbox>
			<xmin>665</xmin>
			<ymin>524</ymin>
			<xmax>709</xmax>
			<ymax>562</ymax>
		</bndbox>
	</object>
	<object>
		<name>spikelet</name>
		<pose>Unspecified</pose>
		<truncated>1</truncated>
		<difficult>0</difficult>
		<bndbox>
			<xmin>775</xmin>
			<ymin>43</ymin>
			<xmax>800</xmax>
			<ymax>83</ymax>
		</bndbox>
	</object>
	<object>
		<name>spikelet</name>
		<pose>Unspecified</pose>
		<truncated>0</truncated>
		<difficult>0</difficult>
		<bndbox>
			<xmin>460</xmin>
			<ymin>468</ymin>
			<xmax>504</xmax>
			<ymax>508</ymax>
		</bndbox>
	</object>
	<object>
		<name>spikelet</name>
		<pose>Unspecified</pose>
		<truncated>0</truncated>
		<difficult>0</difficult>
		<bndbox>
			<xmin>59</xmin>
			<ymin>124</ymin>
			<xmax>103</xmax>
			<ymax>164</ymax>
		</bndbox>
	</object>
	<object>
		<name>spikelet</name>
		<pose>Unspecified</pose>
		<truncated>0</truncated>
		<difficult>0</difficult>
		<bndbox>
			<xmin>437</xmin>
			<ymin>65</ymin>
			<xmax>469</xmax>
			<ymax>102</ymax>
		</bndbox>
	</object>
	<object>
		<name>spikelet</name>
		<pose>Unspecified</pose>
		<truncated>0</truncated>
		<difficult>0</difficult>
		<bndbox>
			<xmin>488</xmin>
			<ymin>113</ymin>
			<xmax>531</xmax>
			<ymax>148</ymax>
		</bndbox>
	</object>
	<object>
		<name>spikelet</name>
		<pose>Unspecified</pose>
		<truncated>0</truncated>
		<difficult>0</difficult>
		<bndbox>
			<xmin>261</xmin>
			<ymin>73</ymin>
			<xmax>291</xmax>
			<ymax>105</ymax>
		</bndbox>
	</object>
	<object>
		<name>spikelet</name>
		<pose>Unspecified</pose>
		<truncated>0</truncated>
		<difficult>0</difficult>
		<bndbox>
			<xmin>315</xmin>
			<ymin>141</ymin>
			<xmax>341</xmax>
			<ymax>171</ymax>
		</bndbox>
	</object>
	<object>
		<name>spikelet</name>
		<pose>Unspecified</pose>
		<truncated>0</truncated>
		<difficult>0</difficult>
		<bndbox>
			<xmin>128</xmin>
			<ymin>87</ymin>
			<xmax>169</xmax>
			<ymax>127</ymax>
		</bndbox>
	</object>
	<object>
		<name>spikelet</name>
		<pose>Unspecified</pose>
		<truncated>0</truncated>
		<difficult>0</difficult>
		<bndbox>
			<xmin>707</xmin>
			<ymin>550</ymin>
			<xmax>745</xmax>
			<ymax>586</ymax>
		</bndbox>
	</object>
	<object>
		<name>spikelet</name>
		<pose>Unspecified</pose>
		<truncated>0</truncated>
		<difficult>0</difficult>
		<bndbox>
			<xmin>671</xmin>
			<ymin>564</ymin>
			<xmax>707</xmax>
			<ymax>598</ymax>
		</bndbox>
	</object>
</annotation>
