<annotation>
	<folder>FINAL_XML_DATASET_NEW</folder>
	<filename>260_001.png</filename>
	<path>/media/ivliev/DISK/_dataset/FINAL_XML_DATASET_NEW/260_001.png</path>
	<source>
		<database>Unknown</database>
	</source>
	<size>
		<width>800</width>
		<height>800</height>
		<depth>3</depth>
	</size>
	<segmented>0</segmented>
	<object>
		<name>weed</name>
		<pose>Unspecified</pose>
		<truncated>0</truncated>
		<difficult>0</difficult>
		<bndbox>
			<xmin>644</xmin>
			<ymin>133</ymin>
			<xmax>686</xmax>
			<ymax>173</ymax>
		</bndbox>
	</object>
	<object>
		<name>weed</name>
		<pose>Unspecified</pose>
		<truncated>0</truncated>
		<difficult>0</difficult>
		<bndbox>
			<xmin>680</xmin>
			<ymin>208</ymin>
			<xmax>735</xmax>
			<ymax>244</ymax>
		</bndbox>
	</object>
	<object>
		<name>weed</name>
		<pose>Unspecified</pose>
		<truncated>0</truncated>
		<difficult>0</difficult>
		<bndbox>
			<xmin>680</xmin>
			<ymin>490</ymin>
			<xmax>731</xmax>
			<ymax>523</ymax>
		</bndbox>
	</object>
	<object>
		<name>spikelet</name>
		<pose>Unspecified</pose>
		<truncated>0</truncated>
		<difficult>0</difficult>
		<bndbox>
			<xmin>467</xmin>
			<ymin>135</ymin>
			<xmax>565</xmax>
			<ymax>206</ymax>
		</bndbox>
	</object>
	<object>
		<name>spikelet</name>
		<pose>Unspecified</pose>
		<truncated>0</truncated>
		<difficult>0</difficult>
		<bndbox>
			<xmin>332</xmin>
			<ymin>198</ymin>
			<xmax>421</xmax>
			<ymax>272</ymax>
		</bndbox>
	</object>
	<object>
		<name>spikelet</name>
		<pose>Unspecified</pose>
		<truncated>0</truncated>
		<difficult>0</difficult>
		<bndbox>
			<xmin>291</xmin>
			<ymin>699</ymin>
			<xmax>422</xmax>
			<ymax>783</ymax>
		</bndbox>
	</object>
	<object>
		<name>spikelet</name>
		<pose>Unspecified</pose>
		<truncated>0</truncated>
		<difficult>0</difficult>
		<bndbox>
			<xmin>138</xmin>
			<ymin>418</ymin>
			<xmax>185</xmax>
			<ymax>467</ymax>
		</bndbox>
	</object>
	<object>
		<name>spikelet</name>
		<pose>Unspecified</pose>
		<truncated>1</truncated>
		<difficult>0</difficult>
		<bndbox>
			<xmin>25</xmin>
			<ymin>1</ymin>
			<xmax>86</xmax>
			<ymax>59</ymax>
		</bndbox>
	</object>
	<object>
		<name>spikelet</name>
		<pose>Unspecified</pose>
		<truncated>1</truncated>
		<difficult>0</difficult>
		<bndbox>
			<xmin>1</xmin>
			<ymin>217</ymin>
			<xmax>107</xmax>
			<ymax>272</ymax>
		</bndbox>
	</object>
	<object>
		<name>spikelet</name>
		<pose>Unspecified</pose>
		<truncated>0</truncated>
		<difficult>0</difficult>
		<bndbox>
			<xmin>111</xmin>
			<ymin>199</ymin>
			<xmax>141</xmax>
			<ymax>282</ymax>
		</bndbox>
	</object>
	<object>
		<name>spikelet</name>
		<pose>Unspecified</pose>
		<truncated>0</truncated>
		<difficult>0</difficult>
		<bndbox>
			<xmin>392</xmin>
			<ymin>350</ymin>
			<xmax>488</xmax>
			<ymax>389</ymax>
		</bndbox>
	</object>
	<object>
		<name>spikelet</name>
		<pose>Unspecified</pose>
		<truncated>0</truncated>
		<difficult>0</difficult>
		<bndbox>
			<xmin>513</xmin>
			<ymin>594</ymin>
			<xmax>635</xmax>
			<ymax>618</ymax>
		</bndbox>
	</object>
	<object>
		<name>spikelet</name>
		<pose>Unspecified</pose>
		<truncated>0</truncated>
		<difficult>0</difficult>
		<bndbox>
			<xmin>338</xmin>
			<ymin>637</ymin>
			<xmax>405</xmax>
			<ymax>687</ymax>
		</bndbox>
	</object>
	<object>
		<name>spikelet</name>
		<pose>Unspecified</pose>
		<truncated>1</truncated>
		<difficult>0</difficult>
		<bndbox>
			<xmin>711</xmin>
			<ymin>314</ymin>
			<xmax>800</xmax>
			<ymax>379</ymax>
		</bndbox>
	</object>
	<object>
		<name>spikelet</name>
		<pose>Unspecified</pose>
		<truncated>0</truncated>
		<difficult>0</difficult>
		<bndbox>
			<xmin>270</xmin>
			<ymin>553</ymin>
			<xmax>340</xmax>
			<ymax>637</ymax>
		</bndbox>
	</object>
	<object>
		<name>spikelet</name>
		<pose>Unspecified</pose>
		<truncated>0</truncated>
		<difficult>0</difficult>
		<bndbox>
			<xmin>8</xmin>
			<ymin>440</ymin>
			<xmax>80</xmax>
			<ymax>499</ymax>
		</bndbox>
	</object>
	<object>
		<name>spikelet</name>
		<pose>Unspecified</pose>
		<truncated>0</truncated>
		<difficult>0</difficult>
		<bndbox>
			<xmin>170</xmin>
			<ymin>162</ymin>
			<xmax>219</xmax>
			<ymax>216</ymax>
		</bndbox>
	</object>
</annotation>
