<annotation>
	<folder>FINAL_XML_DATASET_NEW</folder>
	<filename>429_001.png</filename>
	<path>/media/ivliev/DISK/_dataset/FINAL_XML_DATASET_NEW/429_001.png</path>
	<source>
		<database>Unknown</database>
	</source>
	<size>
		<width>800</width>
		<height>800</height>
		<depth>3</depth>
	</size>
	<segmented>0</segmented>
	<object>
		<name>weed</name>
		<pose>Unspecified</pose>
		<truncated>0</truncated>
		<difficult>0</difficult>
		<bndbox>
			<xmin>303</xmin>
			<ymin>130</ymin>
			<xmax>361</xmax>
			<ymax>181</ymax>
		</bndbox>
	</object>
	<object>
		<name>weed</name>
		<pose>Unspecified</pose>
		<truncated>1</truncated>
		<difficult>0</difficult>
		<bndbox>
			<xmin>1</xmin>
			<ymin>581</ymin>
			<xmax>218</xmax>
			<ymax>800</ymax>
		</bndbox>
	</object>
	<object>
		<name>weed</name>
		<pose>Unspecified</pose>
		<truncated>0</truncated>
		<difficult>0</difficult>
		<bndbox>
			<xmin>162</xmin>
			<ymin>373</ymin>
			<xmax>232</xmax>
			<ymax>415</ymax>
		</bndbox>
	</object>
	<object>
		<name>spikelet</name>
		<pose>Unspecified</pose>
		<truncated>0</truncated>
		<difficult>0</difficult>
		<bndbox>
			<xmin>667</xmin>
			<ymin>513</ymin>
			<xmax>722</xmax>
			<ymax>571</ymax>
		</bndbox>
	</object>
	<object>
		<name>spikelet</name>
		<pose>Unspecified</pose>
		<truncated>0</truncated>
		<difficult>0</difficult>
		<bndbox>
			<xmin>698</xmin>
			<ymin>110</ymin>
			<xmax>787</xmax>
			<ymax>146</ymax>
		</bndbox>
	</object>
	<object>
		<name>spikelet</name>
		<pose>Unspecified</pose>
		<truncated>0</truncated>
		<difficult>0</difficult>
		<bndbox>
			<xmin>614</xmin>
			<ymin>616</ymin>
			<xmax>729</xmax>
			<ymax>647</ymax>
		</bndbox>
	</object>
</annotation>
